{
  "DLSVersion": "2.1.6",
  "Name": "CPU",
  "NameLocation": 0,
  "ChipType": 0,
  "Size": {
    "x": 0.575,
    "y": 1.75
  },
  "Colour": {
    "r": 0.955422342,
    "g": 0.07049397,
    "b": 0.144885421,
    "a": 1
  },
  "InputPins":[
    {
      "Name":"PC0",
      "ID":480948487,
      "Position":{
        "x":-11.06968,
        "y":18.03049
      },
      "BitCount":1,
      "Colour":0,
      "ValueDisplayMode":0
    },
    {
      "Name":"POWER",
      "ID":340907181,
      "Position":{
        "x":-11.51112,
        "y":14.43103
      },
      "BitCount":1,
      "Colour":0,
      "ValueDisplayMode":0
    },
    {
      "Name":"CLK",
      "ID":782041870,
      "Position":{
        "x":-11.49232,
        "y":13.89773
      },
      "BitCount":1,
      "Colour":0,
      "ValueDisplayMode":0
    },
    {
      "Name":"SWITCH",
      "ID":530063015,
      "Position":{
        "x":-11.49988,
        "y":13.35695
      },
      "BitCount":1,
      "Colour":0,
      "ValueDisplayMode":0
    }
  ],
  "OutputPins":[
    {
      "Name":"SCR",
      "ID":812176318,
      "Position":{
        "x":9.99504,
        "y":19.84024
      },
      "BitCount":8,
      "Colour":0,
      "ValueDisplayMode":1
    },
    {
      "Name":"PC",
      "ID":709133615,
      "Position":{
        "x":-4.31384,
        "y":17.67764
      },
      "BitCount":8,
      "Colour":0,
      "ValueDisplayMode":1
    }
  ],
  "SubChips":[
    {
      "Name":"ALU",
      "ID":347799747,
      "Label":"",
      "Position":{
        "x":4.0528,
        "y":15.00812
      },
      "OutputPinColourInfo":[{"PinColour":0,"PinID":793829837},{"PinColour":0,"PinID":265357649}],
      "InternalData":null
    },
    {
      "Name":"8CREG",
      "ID":45919798,
      "Label":"ACCUM",
      "Position":{
        "x":7.74072,
        "y":13.25925
      },
      "OutputPinColourInfo":[{"PinColour":5,"PinID":1665930128}],
      "InternalData":null
    },
    {
      "Name":"8MUX",
      "ID":143968574,
      "Label":"",
      "Position":{
        "x":5.10644,
        "y":14.07121
      },
      "OutputPinColourInfo":[{"PinColour":0,"PinID":473240458}],
      "InternalData":null
    },
    {
      "Name":"ROM 256×16",
      "ID":849236913,
      "Label":"PROG",
      "Position":{
        "x":-4.11422,
        "y":18.96201
      },
      "OutputPinColourInfo":[{"PinColour":0,"PinID":1},{"PinColour":4,"PinID":2}],
      "InternalData":[1544,2048,1543,2049,1536,2050,1793,2816,1794,256,2050,1792,2561,512,2048,1030,1794,2304,0,0,0,0,0,0,0,0,0,0,0,0,0,0,0,0,0,0,0,0,0,0,0,0,0,0,0,0,0,0,0,0,0,0,0,0,0,0,0,0,0,0,0,0,0,0,0,0,0,0,0,0,0,0,0,0,0,0,0,0,0,0,0,0,0,0,0,0,0,0,0,0,0,0,0,0,0,0,0,0,0,0,0,0,0,0,0,0,0,0,0,0,0,0,0,0,0,0,0,0,0,0,0,0,0,0,0,0,0,0,0,0,0,0,0,0,0,0,0,0,0,0,0,0,0,0,0,0,0,0,0,0,0,0,0,0,0,0,0,0,0,0,0,0,0,0,0,0,0,0,0,0,0,0,0,0,0,0,0,0,0,0,0,0,0,0,0,0,0,0,0,0,0,0,0,0,0,0,0,0,0,0,0,0,0,0,0,0,0,0,0,0,0,0,0,0,0,0,0,0,0,0,0,0,0,0,0,0,0,0,0,0,0,0,0,0,0,0,0,0,0,0,0,0,0,0,0,0,0,0,0,0,0,0,0,0,0,0]
    },
    {
      "Name":"OPDEC",
      "ID":930275153,
      "Label":"",
      "Position":{
        "x":-1.72034,
        "y":19.21604
      },
      "OutputPinColourInfo":[{"PinColour":0,"PinID":88312651},{"PinColour":0,"PinID":647333541},{"PinColour":0,"PinID":1665387619},{"PinColour":3,"PinID":1373491805},{"PinColour":3,"PinID":1892196422},{"PinColour":3,"PinID":1015173793},{"PinColour":3,"PinID":260288361},{"PinColour":3,"PinID":1295204846},{"PinColour":3,"PinID":1823867333},{"PinColour":3,"PinID":8937742},{"PinColour":3,"PinID":562401754},{"PinColour":3,"PinID":1839903119},{"PinColour":3,"PinID":5643300},{"PinColour":3,"PinID":1591233629}],
      "InternalData":null
    },
    {
      "Name":"BUS-8",
      "ID":2137147351,
      "Label":"",
      "Position":{
        "x":-1.52396,
        "y":17.06653
      },
      "OutputPinColourInfo":null,
      "InternalData":[213780186,0]
    },
    {
      "Name":"BUS-TERMINUS-8",
      "ID":213780186,
      "Label":"",
      "Position":{
        "x":-1.24865,
        "y":10.33754
      },
      "OutputPinColourInfo":null,
      "InternalData":[2137147351,0]
    },
    {
      "Name":"AND",
      "ID":796856772,
      "Label":"",
      "Position":{
        "x":2.15047,
        "y":18.52273
      },
      "OutputPinColourInfo":[{"PinColour":0,"PinID":1996807063}],
      "InternalData":null
    },
    {
      "Name":"8MUX",
      "ID":465775410,
      "Label":"",
      "Position":{
        "x":-8.76495,
        "y":19.13919
      },
      "OutputPinColourInfo":[{"PinColour":0,"PinID":473240458}],
      "InternalData":null
    },
    {
      "Name":"4OR",
      "ID":182270017,
      "Label":"",
      "Position":{
        "x":-7.8473,
        "y":17.133
      },
      "OutputPinColourInfo":[{"PinColour":0,"PinID":572920859}],
      "InternalData":null
    },
    {
      "Name":"8Z",
      "ID":759755078,
      "Label":"",
      "Position":{
        "x":4.24558,
        "y":16.92331
      },
      "OutputPinColourInfo":[{"PinColour":0,"PinID":1778535134}],
      "InternalData":null
    },
    {
      "Name":"AND",
      "ID":1833140986,
      "Label":"",
      "Position":{
        "x":4.91419,
        "y":17.7894
      },
      "OutputPinColourInfo":[{"PinColour":0,"PinID":1996807063}],
      "InternalData":null
    },
    {
      "Name":"8RAM256",
      "ID":1408447547,
      "Label":"",
      "Position":{
        "x":3.18797,
        "y":12.47167
      },
      "OutputPinColourInfo":[{"PinColour":0,"PinID":289446412}],
      "InternalData":null
    },
    {
      "Name":"8MUX",
      "ID":1198921146,
      "Label":"",
      "Position":{
        "x":6.23328,
        "y":13.37898
      },
      "OutputPinColourInfo":[{"PinColour":0,"PinID":473240458}],
      "InternalData":null
    },
    {
      "Name":"AND",
      "ID":1668912195,
      "Label":"",
      "Position":{
        "x":-8.2632,
        "y":14.21605
      },
      "OutputPinColourInfo":[{"PinColour":7,"PinID":1996807063}],
      "InternalData":null
    },
    {
      "Name":"8PC2",
      "ID":327376150,
      "Label":"",
      "Position":{
        "x":-6.28201,
        "y":18.9352
      },
      "OutputPinColourInfo":[{"PinColour":0,"PinID":868523988}],
      "InternalData":null
    },
    {
      "Name":"CLOCK",
      "ID":951803853,
      "Label":"",
      "Position":{
        "x":-10.7326,
        "y":12.73085
      },
      "OutputPinColourInfo":[{"PinColour":0,"PinID":0}],
      "InternalData":null
    },
    {
      "Name":"8CREG",
      "ID":1781784850,
      "Label":"",
      "Position":{
        "x":7.2618,
        "y":19.8357
      },
      "OutputPinColourInfo":[{"PinColour":0,"PinID":1665930128}],
      "InternalData":null
    },
    {
      "Name":"AND",
      "ID":999214923,
      "Label":"",
      "Position":{
        "x":3.54603,
        "y":19.5894
      },
      "OutputPinColourInfo":[{"PinColour":0,"PinID":1996807063}],
      "InternalData":null
    },
    {
      "Name":"BUS-1",
      "ID":419601444,
      "Label":"CLK",
      "Position":{
        "x":-9.95385,
        "y":15.47684
      },
      "OutputPinColourInfo":null,
      "InternalData":[112814756,0]
    },
    {
      "Name":"BUS-TERMINUS-1",
      "ID":112814756,
      "Label":"",
      "Position":{
        "x":7.97613,
        "y":15.61286
      },
      "OutputPinColourInfo":null,
      "InternalData":[419601444,0]
    },
    {
      "Name":"8CREG",
      "ID":1110340763,
      "Label":"",
      "Position":{
        "x":1.09371,
        "y":14.86247
      },
      "OutputPinColourInfo":[{"PinColour":0,"PinID":1665930128}],
      "InternalData":null
    },
    {
      "Name":"AND",
      "ID":400698322,
      "Label":"",
      "Position":{
        "x":-0.22729,
        "y":14.74762
      },
      "OutputPinColourInfo":[{"PinColour":0,"PinID":1996807063}],
      "InternalData":null
    },
    {
      "Name":"8MUX",
      "ID":72900041,
      "Label":"",
      "Position":{
        "x":-0.1859,
        "y":16.13058
      },
      "OutputPinColourInfo":[{"PinColour":0,"PinID":473240458}],
      "InternalData":null
    },
    {
      "Name":"OR",
      "ID":1388096854,
      "Label":"",
      "Position":{
        "x":0.08342,
        "y":20.40707
      },
      "OutputPinColourInfo":[{"PinColour":0,"PinID":2054622877}],
      "InternalData":null
    },
    {
      "Name":"DOT DISPLAY",
      "ID":500057745,
      "Label":"",
      "Position":{
        "x":9.27333,
        "y":17.50688
      },
      "OutputPinColourInfo":[{"PinColour":0,"PinID":6}],
      "InternalData":null
    },
    {
      "Name":"8Z",
      "ID":933732877,
      "Label":"",
      "Position":{
        "x":6.90689,
        "y":17.71335
      },
      "OutputPinColourInfo":[{"PinColour":0,"PinID":1778535134}],
      "InternalData":null
    },
    {
      "Name":"N",
      "ID":403940911,
      "Label":"",
      "Position":{
        "x":7.73669,
        "y":17.73195
      },
      "OutputPinColourInfo":[{"PinColour":0,"PinID":1208482351}],
      "InternalData":null
    },
    {
      "Name":"DL",
      "ID":1962883147,
      "Label":"",
      "Position":{
        "x":2.23393,
        "y":17.28074
      },
      "OutputPinColourInfo":[{"PinColour":0,"PinID":1364462093},{"PinColour":0,"PinID":1828305822}],
      "InternalData":null
    },
    {
      "Name":"MUX",
      "ID":1738884816,
      "Label":"",
      "Position":{
        "x":-9.2723,
        "y":13.83329
      },
      "OutputPinColourInfo":[{"PinColour":0,"PinID":1698967697}],
      "InternalData":null
    },
    {
      "Name":"8MUX",
      "ID":585689815,
      "Label":"",
      "Position":{
        "x":2.51048,
        "y":14.98424
      },
      "OutputPinColourInfo":[{"PinColour":0,"PinID":473240458}],
      "InternalData":null
    },
    {
      "Name":"OR",
      "ID":148701838,
      "Label":"",
      "Position":{
        "x":1.10843,
        "y":14.16937
      },
      "OutputPinColourInfo":[{"PinColour":0,"PinID":2054622877}],
      "InternalData":null
    },
    {
      "Name":"AND",
      "ID":1751333767,
      "Label":"",
      "Position":{
        "x":-0.06924,
        "y":12.47542
      },
      "OutputPinColourInfo":[{"PinColour":0,"PinID":1996807063}],
      "InternalData":null
    },
    {
      "Name":"8MUX",
      "ID":1694873900,
      "Label":"",
      "Position":{
        "x":1.59169,
        "y":11.7686
      },
      "OutputPinColourInfo":[{"PinColour":0,"PinID":473240458}],
      "InternalData":null
    },
    {
      "Name":"8AND",
      "ID":139386115,
      "Label":"",
      "Position":{
        "x":-0.32518,
        "y":11.24949
      },
      "OutputPinColourInfo":[{"PinColour":0,"PinID":1332830129}],
      "InternalData":null
    },
    {
      "Name":"N",
      "ID":928015125,
      "Label":"",
      "Position":{
        "x":3.93774,
        "y":17.6377
      },
      "OutputPinColourInfo":[{"PinColour":0,"PinID":1208482351}],
      "InternalData":null
    }
  ],
  "Wires":[
    {
      "SourcePinAddress":{
        "PinID":1665930128,
        "PinOwnerID":45919798
      },
      "TargetPinAddress":{
        "PinID":989365775,
        "PinOwnerID":347799747
      },
      "ConnectionType":0,
      "ConnectedWireIndex":-1,
      "ConnectedWireSegmentIndex":-1,
      "Points":[{"x":0.0,"y":0.0},{"x":8.96612,"y":13.53108},{"x":8.9573,"y":16.05421},{"x":3.26463,"y":15.97801},{"x":3.26463,"y":15.36995},{"x":0.0,"y":0.0}]
    },
    {
      "SourcePinAddress":{
        "PinID":265357649,
        "PinOwnerID":347799747
      },
      "TargetPinAddress":{
        "PinID":2013762176,
        "PinOwnerID":143968574
      },
      "ConnectionType":0,
      "ConnectedWireIndex":-1,
      "ConnectedWireSegmentIndex":-1,
      "Points":[{"x":0.0,"y":0.0},{"x":0.0,"y":0.0}]
    },
    {
      "SourcePinAddress":{
        "PinID":1,
        "PinOwnerID":2137147351
      },
      "TargetPinAddress":{
        "PinID":0,
        "PinOwnerID":213780186
      },
      "ConnectionType":0,
      "ConnectedWireIndex":-1,
      "ConnectedWireSegmentIndex":-1,
      "Points":[{"x":0.0,"y":0.0},{"x":0.0,"y":0.0}]
    },
    {
      "SourcePinAddress":{
        "PinID":1,
        "PinOwnerID":2137147351
      },
      "TargetPinAddress":{
        "PinID":316480967,
        "PinOwnerID":143968574
      },
      "ConnectionType":1,
      "ConnectedWireIndex":2,
      "ConnectedWireSegmentIndex":0,
      "Points":[{"x":-1.38646,"y":13.89763},{"x":0.0,"y":0.0}]
    },
    {
      "SourcePinAddress":{
        "PinID":8937742,
        "PinOwnerID":930275153
      },
      "TargetPinAddress":{
        "PinID":896685307,
        "PinOwnerID":796856772
      },
      "ConnectionType":0,
      "ConnectedWireIndex":-1,
      "ConnectedWireSegmentIndex":-1,
      "Points":[{"x":0.0,"y":0.0},{"x":0.0,"y":0.0}]
    },
    {
      "SourcePinAddress":{
        "PinID":1823867333,
        "PinOwnerID":930275153
      },
      "TargetPinAddress":{
        "PinID":708683183,
        "PinOwnerID":143968574
      },
      "ConnectionType":0,
      "ConnectedWireIndex":-1,
      "ConnectedWireSegmentIndex":-1,
      "Points":[{"x":0.0,"y":0.0},{"x":0.22461,"y":18.90652},{"x":0.26417,"y":13.52245},{"x":0.0,"y":0.0}]
    },
    {
      "SourcePinAddress":{
        "PinID":1839903119,
        "PinOwnerID":930275153
      },
      "TargetPinAddress":{
        "PinID":875400935,
        "PinOwnerID":182270017
      },
      "ConnectionType":0,
      "ConnectedWireIndex":-1,
      "ConnectedWireSegmentIndex":-1,
      "Points":[{"x":0.0,"y":0.0},{"x":-0.33235,"y":18.1609},{"x":-0.32813,"y":16.2086},{"x":-8.24583,"y":16.2086},{"x":-8.24583,"y":16.79383},{"x":0.0,"y":0.0}]
    },
    {
      "SourcePinAddress":{
        "PinID":1996807063,
        "PinOwnerID":796856772
      },
      "TargetPinAddress":{
        "PinID":335521439,
        "PinOwnerID":182270017
      },
      "ConnectionType":0,
      "ConnectedWireIndex":-1,
      "ConnectedWireSegmentIndex":-1,
      "Points":[{"x":0.0,"y":0.0},{"x":2.92271,"y":18.52582},{"x":2.93075,"y":16.49548},{"x":-8.42943,"y":16.49548},{"x":-8.42943,"y":17.02332},{"x":0.0,"y":0.0}]
    },
    {
      "SourcePinAddress":{
        "PinID":2,
        "PinOwnerID":849236913
      },
      "TargetPinAddress":{
        "PinID":0,
        "PinOwnerID":2137147351
      },
      "ConnectionType":2,
      "ConnectedWireIndex":2,
      "ConnectedWireSegmentIndex":0,
      "Points":[{"x":0.0,"y":0.0},{"x":-2.65508,"y":18.72022},{"x":-2.62368,"y":15.72996},{"x":-1.38791,"y":15.73001}]
    },
    {
      "SourcePinAddress":{
        "PinID":1,
        "PinOwnerID":2137147351
      },
      "TargetPinAddress":{
        "PinID":2013762176,
        "PinOwnerID":465775410
      },
      "ConnectionType":1,
      "ConnectedWireIndex":2,
      "ConnectedWireSegmentIndex":0,
      "Points":[{"x":-1.38743,"y":15.13192},{"x":-9.08777,"y":15.13185},{"x":0.0,"y":0.0}]
    },
    {
      "SourcePinAddress":{
        "PinID":5643300,
        "PinOwnerID":930275153
      },
      "TargetPinAddress":{
        "PinID":569167105,
        "PinOwnerID":347799747
      },
      "ConnectionType":0,
      "ConnectedWireIndex":-1,
      "ConnectedWireSegmentIndex":-1,
      "Points":[{"x":0.0,"y":0.0},{"x":1.0452,"y":17.8735},{"x":1.06154,"y":14.44051},{"x":0.0,"y":0.0}]
    },
    {
      "SourcePinAddress":{
        "PinID":1665930128,
        "PinOwnerID":45919798
      },
      "TargetPinAddress":{
        "PinID":1988536536,
        "PinOwnerID":759755078
      },
      "ConnectionType":1,
      "ConnectedWireIndex":0,
      "ConnectedWireSegmentIndex":2,
      "Points":[{"x":3.39304,"y":15.97973},{"x":3.40576,"y":16.92643},{"x":0.0,"y":0.0}]
    },
    {
      "SourcePinAddress":{
        "PinID":562401754,
        "PinOwnerID":930275153
      },
      "TargetPinAddress":{
        "PinID":896685307,
        "PinOwnerID":1833140986
      },
      "ConnectionType":0,
      "ConnectedWireIndex":-1,
      "ConnectedWireSegmentIndex":-1,
      "Points":[{"x":0.0,"y":0.0},{"x":0.01452,"y":18.39449},{"x":0.00151,"y":17.9797},{"x":0.0,"y":0.0}]
    },
    {
      "SourcePinAddress":{
        "PinID":0,
        "PinOwnerID":480948487
      },
      "TargetPinAddress":{
        "PinID":90008500,
        "PinOwnerID":182270017
      },
      "ConnectionType":0,
      "ConnectedWireIndex":-1,
      "ConnectedWireSegmentIndex":-1,
      "Points":[{"x":0.0,"y":0.0},{"x":-10.30633,"y":17.48566},{"x":0.0,"y":0.0}]
    },
    {
      "SourcePinAddress":{
        "PinID":1996807063,
        "PinOwnerID":1833140986
      },
      "TargetPinAddress":{
        "PinID":2091043511,
        "PinOwnerID":182270017
      },
      "ConnectionType":0,
      "ConnectedWireIndex":-1,
      "ConnectedWireSegmentIndex":-1,
      "Points":[{"x":0.0,"y":0.0},{"x":5.62206,"y":17.77842},{"x":5.62206,"y":16.33704},{"x":-8.67197,"y":16.36732},{"x":-8.67197,"y":17.25847},{"x":0.0,"y":0.0}]
    },
    {
      "SourcePinAddress":{
        "PinID":1208482351,
        "PinOwnerID":928015125
      },
      "TargetPinAddress":{
        "PinID":1003058654,
        "PinOwnerID":1833140986
      },
      "ConnectionType":0,
      "ConnectedWireIndex":-1,
      "ConnectedWireSegmentIndex":-1,
      "Points":[{"x":0.0,"y":0.0},{"x":0.0,"y":0.0}]
    },
    {
      "SourcePinAddress":{
        "PinID":1665930128,
        "PinOwnerID":45919798
      },
      "TargetPinAddress":{
        "PinID":865515303,
        "PinOwnerID":1408447547
      },
      "ConnectionType":1,
      "ConnectedWireIndex":0,
      "ConnectedWireSegmentIndex":3,
      "Points":[{"x":3.26463,"y":15.36995},{"x":3.26705,"y":13.38388},{"x":2.30667,"y":13.37188},{"x":2.30667,"y":12.83167},{"x":0.0,"y":0.0}]
    },
    {
      "SourcePinAddress":{
        "PinID":473240458,
        "PinOwnerID":143968574
      },
      "TargetPinAddress":{
        "PinID":2013762176,
        "PinOwnerID":1198921146
      },
      "ConnectionType":0,
      "ConnectedWireIndex":-1,
      "ConnectedWireSegmentIndex":-1,
      "Points":[{"x":0.0,"y":0.0},{"x":0.0,"y":0.0}]
    },
    {
      "SourcePinAddress":{
        "PinID":289446412,
        "PinOwnerID":1408447547
      },
      "TargetPinAddress":{
        "PinID":316480967,
        "PinOwnerID":1198921146
      },
      "ConnectionType":0,
      "ConnectedWireIndex":-1,
      "ConnectedWireSegmentIndex":-1,
      "Points":[{"x":0.0,"y":0.0},{"x":4.59314,"y":13.22551},{"x":0.0,"y":0.0}]
    },
    {
      "SourcePinAddress":{
        "PinID":473240458,
        "PinOwnerID":1198921146
      },
      "TargetPinAddress":{
        "PinID":851150943,
        "PinOwnerID":45919798
      },
      "ConnectionType":0,
      "ConnectedWireIndex":-1,
      "ConnectedWireSegmentIndex":-1,
      "Points":[{"x":0.0,"y":0.0},{"x":0.0,"y":0.0}]
    },
    {
      "SourcePinAddress":{
        "PinID":1295204846,
        "PinOwnerID":930275153
      },
      "TargetPinAddress":{
        "PinID":708683183,
        "PinOwnerID":1198921146
      },
      "ConnectionType":0,
      "ConnectedWireIndex":-1,
      "ConnectedWireSegmentIndex":-1,
      "Points":[{"x":0.0,"y":0.0},{"x":0.44114,"y":19.14822},{"x":0.46141,"y":12.66858},{"x":5.50554,"y":12.66858},{"x":0.0,"y":0.0}]
    },
    {
      "SourcePinAddress":{
        "PinID":1,
        "PinOwnerID":849236913
      },
      "TargetPinAddress":{
        "PinID":27414855,
        "PinOwnerID":930275153
      },
      "ConnectionType":0,
      "ConnectedWireIndex":-1,
      "ConnectedWireSegmentIndex":-1,
      "Points":[{"x":0.0,"y":0.0},{"x":0.0,"y":0.0}]
    },
    {
      "SourcePinAddress":{
        "PinID":868523988,
        "PinOwnerID":327376150
      },
      "TargetPinAddress":{
        "PinID":0,
        "PinOwnerID":849236913
      },
      "ConnectionType":0,
      "ConnectedWireIndex":-1,
      "ConnectedWireSegmentIndex":-1,
      "Points":[{"x":0.0,"y":0.0},{"x":0.0,"y":0.0}]
    },
    {
      "SourcePinAddress":{
        "PinID":473240458,
        "PinOwnerID":465775410
      },
      "TargetPinAddress":{
        "PinID":1708443260,
        "PinOwnerID":327376150
      },
      "ConnectionType":0,
      "ConnectedWireIndex":-1,
      "ConnectedWireSegmentIndex":-1,
      "Points":[{"x":0.0,"y":0.0},{"x":0.0,"y":0.0}]
    },
    {
      "SourcePinAddress":{
        "PinID":1778535134,
        "PinOwnerID":759755078
      },
      "TargetPinAddress":{
        "PinID":28496229,
        "PinOwnerID":928015125
      },
      "ConnectionType":0,
      "ConnectedWireIndex":-1,
      "ConnectedWireSegmentIndex":-1,
      "Points":[{"x":0.0,"y":0.0},{"x":4.66102,"y":16.92331},{"x":4.66102,"y":17.32592},{"x":3.34057,"y":17.32592},{"x":3.34057,"y":17.61806},{"x":0.0,"y":0.0}]
    },
    {
      "SourcePinAddress":{
        "PinID":1665930128,
        "PinOwnerID":1781784850
      },
      "TargetPinAddress":{
        "PinID":0,
        "PinOwnerID":812176318
      },
      "ConnectionType":0,
      "ConnectedWireIndex":-1,
      "ConnectedWireSegmentIndex":-1,
      "Points":[{"x":0.0,"y":0.0},{"x":0.0,"y":0.0}]
    },
    {
      "SourcePinAddress":{
        "PinID":1015173793,
        "PinOwnerID":930275153
      },
      "TargetPinAddress":{
        "PinID":896685307,
        "PinOwnerID":999214923
      },
      "ConnectionType":0,
      "ConnectedWireIndex":-1,
      "ConnectedWireSegmentIndex":-1,
      "Points":[{"x":0.0,"y":0.0},{"x":0.0,"y":0.0}]
    },
    {
      "SourcePinAddress":{
        "PinID":1996807063,
        "PinOwnerID":999214923
      },
      "TargetPinAddress":{
        "PinID":1132452528,
        "PinOwnerID":1781784850
      },
      "ConnectionType":0,
      "ConnectedWireIndex":-1,
      "ConnectedWireSegmentIndex":-1,
      "Points":[{"x":0.0,"y":0.0},{"x":0.0,"y":0.0}]
    },
    {
      "SourcePinAddress":{
        "PinID":1,
        "PinOwnerID":419601444
      },
      "TargetPinAddress":{
        "PinID":0,
        "PinOwnerID":112814756
      },
      "ConnectionType":0,
      "ConnectedWireIndex":-1,
      "ConnectedWireSegmentIndex":-1,
      "Points":[{"x":0.0,"y":0.0},{"x":0.0,"y":0.0}]
    },
    {
      "SourcePinAddress":{
        "PinID":1,
        "PinOwnerID":419601444
      },
      "TargetPinAddress":{
        "PinID":1003058654,
        "PinOwnerID":999214923
      },
      "ConnectionType":1,
      "ConnectedWireIndex":28,
      "ConnectedWireSegmentIndex":0,
      "Points":[{"x":3.24864,"y":15.57749},{"x":0.0,"y":0.0}]
    },
    {
      "SourcePinAddress":{
        "PinID":1,
        "PinOwnerID":419601444
      },
      "TargetPinAddress":{
        "PinID":515467955,
        "PinOwnerID":327376150
      },
      "ConnectionType":1,
      "ConnectedWireIndex":28,
      "ConnectedWireSegmentIndex":0,
      "Points":[{"x":-6.64227,"y":15.50131},{"x":0.0,"y":0.0}]
    },
    {
      "SourcePinAddress":{
        "PinID":572920859,
        "PinOwnerID":182270017
      },
      "TargetPinAddress":{
        "PinID":69618865,
        "PinOwnerID":327376150
      },
      "ConnectionType":0,
      "ConnectedWireIndex":-1,
      "ConnectedWireSegmentIndex":-1,
      "Points":[{"x":0.0,"y":0.0},{"x":-7.17119,"y":17.133},{"x":-7.16401,"y":18.79263},{"x":0.0,"y":0.0}]
    },
    {
      "SourcePinAddress":{
        "PinID":1665930128,
        "PinOwnerID":45919798
      },
      "TargetPinAddress":{
        "PinID":851150943,
        "PinOwnerID":1781784850
      },
      "ConnectionType":1,
      "ConnectedWireIndex":0,
      "ConnectedWireSegmentIndex":2,
      "Points":[{"x":6.24328,"y":16.01788},{"x":6.24243,"y":19.9607},{"x":0.0,"y":0.0}]
    },
    {
      "SourcePinAddress":{
        "PinID":1996807063,
        "PinOwnerID":400698322
      },
      "TargetPinAddress":{
        "PinID":1132452528,
        "PinOwnerID":1110340763
      },
      "ConnectionType":0,
      "ConnectedWireIndex":-1,
      "ConnectedWireSegmentIndex":-1,
      "Points":[{"x":0.0,"y":0.0},{"x":0.0,"y":0.0}]
    },
    {
      "SourcePinAddress":{
        "PinID":1,
        "PinOwnerID":419601444
      },
      "TargetPinAddress":{
        "PinID":1003058654,
        "PinOwnerID":400698322
      },
      "ConnectionType":1,
      "ConnectedWireIndex":28,
      "ConnectedWireSegmentIndex":0,
      "Points":[{"x":-0.94959,"y":15.54515},{"x":-0.93113,"y":14.66946},{"x":0.0,"y":0.0}]
    },
    {
      "SourcePinAddress":{
        "PinID":1665930128,
        "PinOwnerID":45919798
      },
      "TargetPinAddress":{
        "PinID":316480967,
        "PinOwnerID":72900041
      },
      "ConnectionType":1,
      "ConnectedWireIndex":0,
      "ConnectedWireSegmentIndex":3,
      "Points":[{"x":3.26463,"y":15.97801},{"x":0.0,"y":0.0}]
    },
    {
      "SourcePinAddress":{
        "PinID":1373491805,
        "PinOwnerID":930275153
      },
      "TargetPinAddress":{
        "PinID":708683183,
        "PinOwnerID":72900041
      },
      "ConnectionType":0,
      "ConnectedWireIndex":-1,
      "ConnectedWireSegmentIndex":-1,
      "Points":[{"x":0.0,"y":0.0},{"x":-0.52916,"y":20.13478},{"x":0.0,"y":0.0}]
    },
    {
      "SourcePinAddress":{
        "PinID":1,
        "PinOwnerID":2137147351
      },
      "TargetPinAddress":{
        "PinID":2013762176,
        "PinOwnerID":72900041
      },
      "ConnectionType":1,
      "ConnectedWireIndex":2,
      "ConnectedWireSegmentIndex":0,
      "Points":[{"x":-1.38852,"y":16.50637},{"x":0.0,"y":0.0}]
    },
    {
      "SourcePinAddress":{
        "PinID":1892196422,
        "PinOwnerID":930275153
      },
      "TargetPinAddress":{
        "PinID":499470854,
        "PinOwnerID":1388096854
      },
      "ConnectionType":0,
      "ConnectedWireIndex":-1,
      "ConnectedWireSegmentIndex":-1,
      "Points":[{"x":0.0,"y":0.0},{"x":-0.82927,"y":19.88333},{"x":-0.82927,"y":20.52412},{"x":0.0,"y":0.0}]
    },
    {
      "SourcePinAddress":{
        "PinID":1373491805,
        "PinOwnerID":930275153
      },
      "TargetPinAddress":{
        "PinID":897253034,
        "PinOwnerID":1388096854
      },
      "ConnectionType":1,
      "ConnectedWireIndex":36,
      "ConnectedWireSegmentIndex":1,
      "Points":[{"x":-0.52916,"y":20.13478},{"x":0.0,"y":0.0}]
    },
    {
      "SourcePinAddress":{
        "PinID":2054622877,
        "PinOwnerID":1388096854
      },
      "TargetPinAddress":{
        "PinID":896685307,
        "PinOwnerID":400698322
      },
      "ConnectionType":0,
      "ConnectedWireIndex":-1,
      "ConnectedWireSegmentIndex":-1,
      "Points":[{"x":0.0,"y":0.0},{"x":0.63672,"y":20.42059},{"x":0.63672,"y":17.30812},{"x":-0.91117,"y":17.30812},{"x":-0.91117,"y":14.91138},{"x":0.0,"y":0.0}]
    },
    {
      "SourcePinAddress":{
        "PinID":1665930128,
        "PinOwnerID":45919798
      },
      "TargetPinAddress":{
        "PinID":0,
        "PinOwnerID":500057745
      },
      "ConnectionType":1,
      "ConnectedWireIndex":32,
      "ConnectedWireSegmentIndex":0,
      "Points":[{"x":6.24283,"y":18.08681},{"x":0.0,"y":0.0}]
    },
    {
      "SourcePinAddress":{
        "PinID":1778535134,
        "PinOwnerID":933732877
      },
      "TargetPinAddress":{
        "PinID":28496229,
        "PinOwnerID":403940911
      },
      "ConnectionType":0,
      "ConnectedWireIndex":-1,
      "ConnectedWireSegmentIndex":-1,
      "Points":[{"x":0.0,"y":0.0},{"x":0.0,"y":0.0}]
    },
    {
      "SourcePinAddress":{
        "PinID":1208482351,
        "PinOwnerID":403940911
      },
      "TargetPinAddress":{
        "PinID":1,
        "PinOwnerID":500057745
      },
      "ConnectionType":0,
      "ConnectedWireIndex":-1,
      "ConnectedWireSegmentIndex":-1,
      "Points":[{"x":0.0,"y":0.0},{"x":0.0,"y":0.0}]
    },
    {
      "SourcePinAddress":{
        "PinID":1,
        "PinOwnerID":2137147351
      },
      "TargetPinAddress":{
        "PinID":1988536536,
        "PinOwnerID":933732877
      },
      "ConnectionType":1,
      "ConnectedWireIndex":3,
      "ConnectedWireSegmentIndex":0,
      "Points":[{"x":4.52935,"y":13.94459},{"x":4.52935,"y":15.13916},{"x":6.19434,"y":15.13916},{"x":6.18574,"y":17.71097},{"x":0.0,"y":0.0}]
    },
    {
      "SourcePinAddress":{
        "PinID":1,
        "PinOwnerID":419601444
      },
      "TargetPinAddress":{
        "PinID":5,
        "PinOwnerID":500057745
      },
      "ConnectionType":1,
      "ConnectedWireIndex":28,
      "ConnectedWireSegmentIndex":0,
      "Points":[{"x":7.5591,"y":15.61069},{"x":7.5591,"y":16.74427},{"x":0.0,"y":0.0}]
    },
    {
      "SourcePinAddress":{
        "PinID":1665387619,
        "PinOwnerID":930275153
      },
      "TargetPinAddress":{
        "PinID":3,
        "PinOwnerID":500057745
      },
      "ConnectionType":0,
      "ConnectedWireIndex":-1,
      "ConnectedWireSegmentIndex":-1,
      "Points":[{"x":0.0,"y":0.0},{"x":5.91238,"y":20.45276},{"x":5.94132,"y":17.19154},{"x":0.0,"y":0.0}]
    },
    {
      "SourcePinAddress":{
        "PinID":647333541,
        "PinOwnerID":930275153
      },
      "TargetPinAddress":{
        "PinID":4,
        "PinOwnerID":500057745
      },
      "ConnectionType":0,
      "ConnectedWireIndex":-1,
      "ConnectedWireSegmentIndex":-1,
      "Points":[{"x":0.0,"y":0.0},{"x":5.71269,"y":20.70048},{"x":5.70636,"y":17.00704},{"x":0.0,"y":0.0}]
    },
    {
      "SourcePinAddress":{
        "PinID":88312651,
        "PinOwnerID":930275153
      },
      "TargetPinAddress":{
        "PinID":2,
        "PinOwnerID":500057745
      },
      "ConnectionType":0,
      "ConnectedWireIndex":-1,
      "ConnectedWireSegmentIndex":-1,
      "Points":[{"x":0.0,"y":0.0},{"x":5.58742,"y":20.89304},{"x":5.58025,"y":18.01655},{"x":5.79108,"y":18.01786},{"x":5.79578,"y":17.44976},{"x":0.0,"y":0.0}]
    },
    {
      "SourcePinAddress":{
        "PinID":793829837,
        "PinOwnerID":347799747
      },
      "TargetPinAddress":{
        "PinID":546459982,
        "PinOwnerID":1962883147
      },
      "ConnectionType":0,
      "ConnectedWireIndex":-1,
      "ConnectedWireSegmentIndex":-1,
      "Points":[{"x":0.0,"y":0.0},{"x":4.34126,"y":16.58841},{"x":1.60386,"y":16.58841},{"x":1.60386,"y":17.36913},{"x":0.0,"y":0.0}]
    },
    {
      "SourcePinAddress":{
        "PinID":5643300,
        "PinOwnerID":930275153
      },
      "TargetPinAddress":{
        "PinID":1189771232,
        "PinOwnerID":1962883147
      },
      "ConnectionType":1,
      "ConnectedWireIndex":10,
      "ConnectedWireSegmentIndex":1,
      "Points":[{"x":1.04862,"y":17.15584},{"x":0.0,"y":0.0}]
    },
    {
      "SourcePinAddress":{
        "PinID":0,
        "PinOwnerID":480948487
      },
      "TargetPinAddress":{
        "PinID":708683183,
        "PinOwnerID":465775410
      },
      "ConnectionType":0,
      "ConnectedWireIndex":-1,
      "ConnectedWireSegmentIndex":-1,
      "Points":[{"x":0.0,"y":0.0},{"x":-10.32786,"y":18.63769},{"x":0.0,"y":0.0}]
    },
    {
      "SourcePinAddress":{
        "PinID":0,
        "PinOwnerID":782041870
      },
      "TargetPinAddress":{
        "PinID":1682716904,
        "PinOwnerID":1738884816
      },
      "ConnectionType":0,
      "ConnectedWireIndex":-1,
      "ConnectedWireSegmentIndex":-1,
      "Points":[{"x":0.0,"y":0.0},{"x":0.0,"y":0.0}]
    },
    {
      "SourcePinAddress":{
        "PinID":1698967697,
        "PinOwnerID":1738884816
      },
      "TargetPinAddress":{
        "PinID":1003058654,
        "PinOwnerID":1668912195
      },
      "ConnectionType":0,
      "ConnectedWireIndex":-1,
      "ConnectedWireSegmentIndex":-1,
      "Points":[{"x":0.0,"y":0.0},{"x":0.0,"y":0.0}]
    },
    {
      "SourcePinAddress":{
        "PinID":0,
        "PinOwnerID":530063015
      },
      "TargetPinAddress":{
        "PinID":1838699397,
        "PinOwnerID":1738884816
      },
      "ConnectionType":0,
      "ConnectedWireIndex":-1,
      "ConnectedWireSegmentIndex":-1,
      "Points":[{"x":0.0,"y":0.0},{"x":0.0,"y":0.0}]
    },
    {
      "SourcePinAddress":{
        "PinID":0,
        "PinOwnerID":951803853
      },
      "TargetPinAddress":{
        "PinID":513648313,
        "PinOwnerID":1738884816
      },
      "ConnectionType":0,
      "ConnectedWireIndex":-1,
      "ConnectedWireSegmentIndex":-1,
      "Points":[{"x":0.0,"y":0.0},{"x":0.0,"y":0.0}]
    },
    {
      "SourcePinAddress":{
        "PinID":1,
        "PinOwnerID":419601444
      },
      "TargetPinAddress":{
        "PinID":1132452528,
        "PinOwnerID":45919798
      },
      "ConnectionType":1,
      "ConnectedWireIndex":28,
      "ConnectedWireSegmentIndex":0,
      "Points":[{"x":6.75463,"y":15.60449},{"x":6.75463,"y":13.01907},{"x":0.0,"y":0.0}]
    },
    {
      "SourcePinAddress":{
        "PinID":473240458,
        "PinOwnerID":585689815
      },
      "TargetPinAddress":{
        "PinID":1455202248,
        "PinOwnerID":347799747
      },
      "ConnectionType":0,
      "ConnectedWireIndex":-1,
      "ConnectedWireSegmentIndex":-1,
      "Points":[{"x":0.0,"y":0.0},{"x":0.0,"y":0.0}]
    },
    {
      "SourcePinAddress":{
        "PinID":2054622877,
        "PinOwnerID":148701838
      },
      "TargetPinAddress":{
        "PinID":708683183,
        "PinOwnerID":585689815
      },
      "ConnectionType":0,
      "ConnectedWireIndex":-1,
      "ConnectedWireSegmentIndex":-1,
      "Points":[{"x":0.0,"y":0.0},{"x":0.0,"y":0.0}]
    },
    {
      "SourcePinAddress":{
        "PinID":1591233629,
        "PinOwnerID":930275153
      },
      "TargetPinAddress":{
        "PinID":499470854,
        "PinOwnerID":148701838
      },
      "ConnectionType":0,
      "ConnectedWireIndex":-1,
      "ConnectedWireSegmentIndex":-1,
      "Points":[{"x":0.0,"y":0.0},{"x":-0.0289,"y":17.61836},{"x":-0.0289,"y":14.27553},{"x":0.0,"y":0.0}]
    },
    {
      "SourcePinAddress":{
        "PinID":5643300,
        "PinOwnerID":930275153
      },
      "TargetPinAddress":{
        "PinID":897253034,
        "PinOwnerID":148701838
      },
      "ConnectionType":1,
      "ConnectedWireIndex":10,
      "ConnectedWireSegmentIndex":1,
      "Points":[{"x":1.0615,"y":14.44839},{"x":0.73846,"y":14.44839},{"x":0.0,"y":0.0}]
    },
    {
      "SourcePinAddress":{
        "PinID":1665930128,
        "PinOwnerID":1110340763
      },
      "TargetPinAddress":{
        "PinID":316480967,
        "PinOwnerID":585689815
      },
      "ConnectionType":0,
      "ConnectedWireIndex":-1,
      "ConnectedWireSegmentIndex":-1,
      "Points":[{"x":0.0,"y":0.0},{"x":0.0,"y":0.0}]
    },
    {
      "SourcePinAddress":{
        "PinID":1996807063,
        "PinOwnerID":1751333767
      },
      "TargetPinAddress":{
        "PinID":1787512495,
        "PinOwnerID":1408447547
      },
      "ConnectionType":0,
      "ConnectedWireIndex":-1,
      "ConnectedWireSegmentIndex":-1,
      "Points":[{"x":0.0,"y":0.0},{"x":0.0,"y":0.0}]
    },
    {
      "SourcePinAddress":{
        "PinID":260288361,
        "PinOwnerID":930275153
      },
      "TargetPinAddress":{
        "PinID":896685307,
        "PinOwnerID":1751333767
      },
      "ConnectionType":0,
      "ConnectedWireIndex":-1,
      "ConnectedWireSegmentIndex":-1,
      "Points":[{"x":0.0,"y":0.0},{"x":-0.67401,"y":19.35183},{"x":-0.69625,"y":12.55769},{"x":0.0,"y":0.0}]
    },
    {
      "SourcePinAddress":{
        "PinID":1,
        "PinOwnerID":419601444
      },
      "TargetPinAddress":{
        "PinID":1003058654,
        "PinOwnerID":1751333767
      },
      "ConnectionType":1,
      "ConnectedWireIndex":34,
      "ConnectedWireSegmentIndex":0,
      "Points":[{"x":-0.9321,"y":14.71556},{"x":-0.9321,"y":12.34635},{"x":0.0,"y":0.0}]
    },
    {
      "SourcePinAddress":{
        "PinID":1996807063,
        "PinOwnerID":1668912195
      },
      "TargetPinAddress":{
        "PinID":0,
        "PinOwnerID":419601444
      },
      "ConnectionType":2,
      "ConnectedWireIndex":28,
      "ConnectedWireSegmentIndex":0,
      "Points":[{"x":0.0,"y":0.0},{"x":-7.96578,"y":15.49111}]
    },
    {
      "SourcePinAddress":{
        "PinID":473240458,
        "PinOwnerID":72900041
      },
      "TargetPinAddress":{
        "PinID":851150943,
        "PinOwnerID":1110340763
      },
      "ConnectionType":0,
      "ConnectedWireIndex":-1,
      "ConnectedWireSegmentIndex":-1,
      "Points":[{"x":0.0,"y":0.0},{"x":0.1866,"y":15.02671},{"x":0.0,"y":0.0}]
    },
    {
      "SourcePinAddress":{
        "PinID":1,
        "PinOwnerID":2137147351
      },
      "TargetPinAddress":{
        "PinID":2013762176,
        "PinOwnerID":1694873900
      },
      "ConnectionType":1,
      "ConnectedWireIndex":2,
      "ConnectedWireSegmentIndex":0,
      "Points":[{"x":-1.38508,"y":12.14367},{"x":0.0,"y":0.0}]
    },
    {
      "SourcePinAddress":{
        "PinID":1665930128,
        "PinOwnerID":1110340763
      },
      "TargetPinAddress":{
        "PinID":316480967,
        "PinOwnerID":1694873900
      },
      "ConnectionType":1,
      "ConnectedWireIndex":61,
      "ConnectedWireSegmentIndex":0,
      "Points":[{"x":1.88376,"y":14.86108},{"x":1.88362,"y":12.83158},{"x":0.67367,"y":12.83158},{"x":0.67367,"y":11.63331},{"x":0.0,"y":0.0}]
    },
    {
      "SourcePinAddress":{
        "PinID":1332830129,
        "PinOwnerID":139386115
      },
      "TargetPinAddress":{
        "PinID":708683183,
        "PinOwnerID":1694873900
      },
      "ConnectionType":0,
      "ConnectedWireIndex":-1,
      "ConnectedWireSegmentIndex":-1,
      "Points":[{"x":0.0,"y":0.0},{"x":0.0,"y":0.0}]
    },
    {
      "SourcePinAddress":{
        "PinID":1,
        "PinOwnerID":2137147351
      },
      "TargetPinAddress":{
        "PinID":2013244497,
        "PinOwnerID":139386115
      },
      "ConnectionType":1,
      "ConnectedWireIndex":2,
      "ConnectedWireSegmentIndex":0,
      "Points":[{"x":-1.38437,"y":11.24945},{"x":0.0,"y":0.0}]
    },
    {
      "SourcePinAddress":{
        "PinID":1828305822,
        "PinOwnerID":1962883147
      },
      "TargetPinAddress":{
        "PinID":1003058654,
        "PinOwnerID":796856772
      },
      "ConnectionType":0,
      "ConnectedWireIndex":-1,
      "ConnectedWireSegmentIndex":-1,
      "Points":[{"x":0.0,"y":0.0},{"x":2.80286,"y":17.15574},{"x":2.80286,"y":18.11414},{"x":1.43365,"y":18.10478},{"x":1.43365,"y":18.38079},{"x":0.0,"y":0.0}]
    },
    {
      "SourcePinAddress":{
        "PinID":473240458,
        "PinOwnerID":1694873900
      },
      "TargetPinAddress":{
        "PinID":488629691,
        "PinOwnerID":1408447547
      },
      "ConnectionType":0,
      "ConnectedWireIndex":-1,
      "ConnectedWireSegmentIndex":-1,
      "Points":[{"x":0.0,"y":0.0},{"x":0.0,"y":0.0}]
    },
    {
      "SourcePinAddress":{
        "PinID":868523988,
        "PinOwnerID":327376150
      },
      "TargetPinAddress":{
        "PinID":0,
        "PinOwnerID":709133615
      },
      "ConnectionType":1,
      "ConnectedWireIndex":22,
      "ConnectedWireSegmentIndex":0,
      "Points":[{"x":-5.45277,"y":18.94703},{"x":0.0,"y":0.0}]
    },
    {
      "SourcePinAddress":{
        "PinID":0,
        "PinOwnerID":340907181
      },
      "TargetPinAddress":{
        "PinID":896685307,
        "PinOwnerID":1668912195
      },
      "ConnectionType":0,
      "ConnectedWireIndex":-1,
      "ConnectedWireSegmentIndex":-1,
      "Points":[{"x":0.0,"y":0.0},{"x":0.0,"y":0.0}]
    }
  ],
  "Displays": null
}